hello.py
fantom_lang-0.1.3.dist-info/licenses/LICENSE
fantom_lang-0.1.3.dist-info/METADATA
fantom_lang-0.1.3.dist-info/WHEEL
fantom_lang-0.1.3.dist-info/top_level.txt
fantom_lang-0.1.3.dist-info/RECORD
